bitmapy/__init__.py
bitmapy/bitmap.py
bitmapy/py.typed
bitmapy-1.0.1.dist-info/WHEEL
bitmapy-1.0.1.dist-info/METADATA
bitmapy-1.0.1.dist-info/RECORD
