Metadata-Version: 2.3
Name: bitmapy
Version: 1.0.1
Summary: Bitmap manipulation and operations.
Author: Oliver Parsons
Author-email: Oliver Parsons <oparsons22@gmail.com>
Requires-Python: >=3.13
Project-URL: source, https://github.com/oparsons22/bitmapy
Project-URL: tracker, https://github.com/oparsons22/bitmapy/issues
